whatthefuzz/mainapi.py
whatthefuzz/wtfconfig.py
whatthefuzz/wtfuzz_core.py
whatthefuzz-0.2.5.dist-info/METADATA
whatthefuzz-0.2.5.dist-info/WHEEL
whatthefuzz-0.2.5.dist-info/top_level.txt
whatthefuzz-0.2.5.dist-info/RECORD
