Metadata-Version: 2.1
Name: whatthefuzz
Version: 0.2.5
Summary: Web fuzzer
Home-page: https://github.com/javixeneize/wtfuzz
Author: Javier Dominguez
Author-email: UNKNOWN
License: UNKNOWN
Platform: UNKNOWN
Requires-Dist: requests (>=2.22.0)
